Metadata-Version: 2.1
Name: ahmadzahoor-distributions
Version: 1.0
Summary: Gaussian and Binomial distributions
Author: Zahoor Ahmad]
Author-email: ahmadzahoor555@gmail.com
